apicrud/__init__.py
apicrud/_version.py
apicrud/access.py
apicrud/account_settings.py
apicrud/aes_encrypt.py
apicrud/alembic.ini
apicrud/basic_crud.py
apicrud/const.py
apicrud/database.py
apicrud/exceptions.py
apicrud/geocode.py
apicrud/grants.py
apicrud/health.py
apicrud/initialize.py
apicrud/metrics.py
apicrud/ratelimit.py
apicrud/service_config.py
apicrud/service_config.yaml
apicrud/service_registry.py
apicrud/session_auth.py
apicrud/session_manager.py
apicrud/state.py
apicrud/timezones.yaml
apicrud/trashcan.py
apicrud/utils.py
apicrud/alembic/README.txt
apicrud/alembic/env.py
apicrud/alembic/script.py.mako
apicrud/alembic/versions/cac2000912a5_initialize.py
apicrud/auth/__init__.py
apicrud/auth/apikey.py
apicrud/auth/ldap_func.py
apicrud/auth/local_func.py
apicrud/auth/local_user.py
apicrud/auth/oauth2.py
apicrud/auth/oauth2_func.py
apicrud/auth/totp.py
apicrud/auth/totp_func.py
apicrud/controllers/account.py
apicrud/controllers/apikey.py
apicrud/controllers/auth.py
apicrud/controllers/category.py
apicrud/controllers/contact.py
apicrud/controllers/credential.py
apicrud/controllers/grant.py
apicrud/controllers/location.py
apicrud/controllers/metric.py
apicrud/controllers/person.py
apicrud/controllers/profile.py
apicrud/controllers/scope.py
apicrud/controllers/settings.py
apicrud/controllers/trashcan.py
apicrud/controllers/tz.py
apicrud/i18n/ar/LC_MESSAGES/messages.mo
apicrud/i18n/de/LC_MESSAGES/messages.mo
apicrud/i18n/en/LC_MESSAGES/messages.mo
apicrud/i18n/es/LC_MESSAGES/messages.mo
apicrud/i18n/fil/LC_MESSAGES/messages.mo
apicrud/i18n/fr/LC_MESSAGES/messages.mo
apicrud/i18n/it/LC_MESSAGES/messages.mo
apicrud/i18n/ja/LC_MESSAGES/messages.mo
apicrud/i18n/ko/LC_MESSAGES/messages.mo
apicrud/i18n/pt/LC_MESSAGES/messages.mo
apicrud/i18n/ru/LC_MESSAGES/messages.mo
apicrud/i18n/vi/LC_MESSAGES/messages.mo
apicrud/i18n/zh/LC_MESSAGES/messages.mo
apicrud/i18n/zh_Hans/LC_MESSAGES/messages.mo
apicrud/i18n/zh_Hant/LC_MESSAGES/messages.mo
apicrud/media/storage.py
apicrud-0.3.6.dist-info/LICENSE.txt
apicrud-0.3.6.dist-info/METADATA
apicrud-0.3.6.dist-info/WHEEL
apicrud-0.3.6.dist-info/top_level.txt
apicrud-0.3.6.dist-info/RECORD
