Metadata-Version: 2.1
Name: apicrud
Version: 0.3.6
Summary: Flask REST framework for role-based access
Home-page: https://github.com/instantlinux/apicrud
Author: Rich Braun
Author-email: docker@instantlinux.net
License: Apache License Version 2.0
Keywords: api flask rbac rest
Classifier: Development Status :: 3 - Alpha
Classifier: License :: OSI Approved :: Apache Software License
Classifier: Topic :: Software Development :: Libraries :: Application Frameworks
Classifier: Intended Audience :: Developers
Classifier: Programming Language :: Python :: 3
Classifier: Programming Language :: Python :: 3.6
Classifier: Programming Language :: Python :: 3.7
Classifier: Programming Language :: Python :: 3.8
Classifier: Programming Language :: Python :: 3.9
Classifier: Programming Language :: Python :: 3.10
Classifier: Programming Language :: Python :: 3.11
Requires-Python: >=3.6
License-File: LICENSE.txt
Requires-Dist: alembic >=1.11.2
Requires-Dist: Authlib <1.0.0,>=0.15.6
Requires-Dist: babel >=2.12.1
Requires-Dist: b2sdk >=1.22.1
Requires-Dist: boto3 >=1.26.132
Requires-Dist: botocore >=1.29.132
Requires-Dist: cachetools >=5.3.1
Requires-Dist: connexion >=2.14.2
Requires-Dist: connexion[swagger-ui]
Requires-Dist: cryptography >=41.0.3
Requires-Dist: Flask <3.0.0,>=2.2.5
Requires-Dist: flask-babel <3.0.0,>=2.0.0
Requires-Dist: Flask-Cors >=4.0.0
Requires-Dist: geocoder >=1.38.1
Requires-Dist: itsdangerous >=2.1.2
Requires-Dist: ldap3 >=2.9.1
Requires-Dist: PyJWT >=2.8.0
Requires-Dist: passlib >=1.7.4
Requires-Dist: pycryptodomex >=3.17
Requires-Dist: pymysql >=1.1.0
Requires-Dist: pyotp >=2.9.0
Requires-Dist: pytz >=2023.3
Requires-Dist: redis >=4.6.0
Requires-Dist: requests >=2.31.0
Requires-Dist: SQLAlchemy <1.4.0,>=1.3.24
Requires-Dist: SQLAlchemy-Utils >=0.41.1
Requires-Dist: swagger-ui-bundle >=0.0.9
Requires-Dist: urllib3 >=1.26.16
